discord_integration/__init__.py
discord_integration/admin.py
discord_integration/apps.py
discord_integration/log.py
discord_integration/models.py
discord_integration/tests.py
discord_integration/views.py
discord_integration/migrations/0001_initial.py
discord_integration/migrations/0002_auto_20200412_1649.py
discord_integration/migrations/0003_discordintegration_name.py
discord_integration/migrations/__init__.py
django_discord_integration-1.2.8.dist-info/LICENSE
django_discord_integration-1.2.8.dist-info/METADATA
django_discord_integration-1.2.8.dist-info/WHEEL
django_discord_integration-1.2.8.dist-info/top_level.txt
django_discord_integration-1.2.8.dist-info/RECORD
